{"cameraMode":{"drawMode":0,"name":"Shaded","section":"Shading Mode"},"sceneLighting":true,"audioPlay":false,"sceneViewState":{"m_AlwaysRefresh":false,"showFog":true,"showSkybox":true,"showFlares":true,"showImageEffects":true,"showParticleSystems":true,"showVisualEffectGraphs":true,"m_FxEnabled":true},"in2DMode":false,"pivot":{"x":23.359325408935548,"y":3.751776933670044,"z":-28.971837997436525},"rotation":{"x":-0.053200121968984607,"y":-0.1939641684293747,"z":0.01085808128118515,"w":-0.9796721339225769},"size":10.540753364562989,"orthographic":false}