{"cameraMode":{"drawMode":0,"name":"Shaded","section":"Shading Mode"},"sceneLighting":false,"audioPlay":false,"sceneViewState":{"m_AlwaysRefresh":false,"showFog":true,"showSkybox":false,"showFlares":true,"showImageEffects":true,"showParticleSystems":true,"showVisualEffectGraphs":true,"m_FxEnabled":true},"in2DMode":false,"pivot":{"x":3.1805922985076906,"y":-7.486794471740723,"z":47.60568618774414},"rotation":{"x":0.017847400158643724,"y":-0.9780654907226563,"z":0.18588075041770936,"w":0.09371555596590042},"size":14.610366821289063,"orthographic":false}